lg_april_permissions/__init__.py
lg_april_permissions-0.1.14.dist-info/METADATA
lg_april_permissions-0.1.14.dist-info/WHEEL
lg_april_permissions-0.1.14.dist-info/entry_points.txt
lg_april_permissions-0.1.14.dist-info/RECORD
